battle/__init__.py
battle/arena.py
battle/chillbot.py
battle/persistence.py
battle/player.py
battle/pongbot.py
battle/radarbot.py
battle/robots.py
battle/runner.py
battle/util.py
battle/static/arena.js
battle/static/lodash.js
battle/static/images/body_01.png
battle/static/images/exhaust_01a.png
battle/static/images/exhaust_01b.png
battle/static/images/galaxy.png
battle/static/images/stars_texture.png
battle/static/images/turret_02_beam_01_anim.png
battle/static/images/turret_02_explosion_01_anim.png
battle/static/images/turret_02_mk1_anim.png
battle/templates/index.html.j2
battle-0.2.1.dist-info/LICENSE.txt
battle-0.2.1.dist-info/METADATA
battle-0.2.1.dist-info/WHEEL
battle-0.2.1.dist-info/entry_points.txt
battle-0.2.1.dist-info/top_level.txt
battle-0.2.1.dist-info/RECORD
