Metadata-Version: 2.1
Name: battle
Version: 0.2.1
Summary: A robot programming game which allows programming a virtual spaceship robot driver with simple commands to fight a battle against other players.
Home-page: https://github.com/atcase/battle
Author: Sasha Case
License: MIT
Platform: UNKNOWN
Classifier: Development Status :: 3 - Alpha
Classifier: Intended Audience :: Education
Classifier: License :: OSI Approved :: MIT License
Classifier: Operating System :: OS Independent
Classifier: Programming Language :: Python :: 3.7
Classifier: Programming Language :: Python :: 3.8
Classifier: Programming Language :: Python :: 3.9
Classifier: Programming Language :: Python :: 3.10
Classifier: Programming Language :: Python :: 3.11
Classifier: Topic :: Education
Classifier: Topic :: Games/Entertainment
Classifier: Topic :: Games/Entertainment :: Simulation
Classifier: Typing :: Typed
License-File: LICENSE.txt
Requires-Dist: websocket-client (>=1.3.1)
Requires-Dist: aiohttp (>=3.8.1)
Requires-Dist: aiohttp-jinja2 (>=1.5)
Requires-Dist: Jinja2 (>=3.0.3)
